djangosubscribe/__init__.py
djangosubscribe/admin.py
djangosubscribe/apps.py
djangosubscribe/urls.py
djangosubscribe/managers/BasicInformationModelManager.py
djangosubscribe/managers/CategoryModelManager.py
djangosubscribe/managers/QuickEmailSubscriptionModelManager.py
djangosubscribe/managers/__init__.py
djangosubscribe/managers/__pycache__/BasicInformationModelManager.cpython-38.pyc
djangosubscribe/managers/__pycache__/CategoryModelManager.cpython-38.pyc
djangosubscribe/managers/__pycache__/QuickEmailSubscriptionModelManager.cpython-38.pyc
djangosubscribe/managers/__pycache__/__init__.cpython-38.pyc
djangosubscribe/migrations/0001_initial.py
djangosubscribe/migrations/__init__.py
djangosubscribe/migrations/__pycache__/0001_initial.cpython-38.pyc
djangosubscribe/migrations/__pycache__/__init__.cpython-38.pyc
djangosubscribe/modeladmins/BasicInformationModelAdmin.py
djangosubscribe/modeladmins/CategoryModelAdmin.py
djangosubscribe/modeladmins/EducationalInformationModelAdmin.py
djangosubscribe/modeladmins/ParentalInformationModelAdmin.py
djangosubscribe/modeladmins/QuickEmailSubscriptionModelAdmin.py
djangosubscribe/modeladmins/WorkInformationModelAdmin.py
djangosubscribe/modeladmins/__init__.py
djangosubscribe/modeladmins/__pycache__/BasicInformationModelAdmin.cpython-38.pyc
djangosubscribe/modeladmins/__pycache__/CategoryModelAdmin.cpython-38.pyc
djangosubscribe/modeladmins/__pycache__/EducationalInformationModelAdmin.cpython-38.pyc
djangosubscribe/modeladmins/__pycache__/ParentalInformationModelAdmin.cpython-38.pyc
djangosubscribe/modeladmins/__pycache__/QuickEmailSubscriptionModelAdmin.cpython-38.pyc
djangosubscribe/modeladmins/__pycache__/WorkInformationModelAdmin.cpython-38.pyc
djangosubscribe/modeladmins/__pycache__/__init__.cpython-38.pyc
djangosubscribe/modelforms/BasicInformationModelForm.py
djangosubscribe/modelforms/CategoryModelForm.py
djangosubscribe/modelforms/EducationalInformationModelForm.py
djangosubscribe-2.2.1.dist-info/License
djangosubscribe-2.2.1.dist-info/METADATA
djangosubscribe-2.2.1.dist-info/WHEEL
djangosubscribe-2.2.1.dist-info/top_level.txt
djangosubscribe-2.2.1.dist-info/RECORD
